Lab4/src/LampCtrl.v
`timescale 1ns / 1ps
//////////////////////////////////////////////////////////////////////////////////
// Company: 
// Engineer: 
// 
// Create Date:    19:56:33 11/20/2024 
// Design Name: 
// Module Name:    LampCtrl 
// Project Name: 
// Target Devices: 
// Tool versions: 
// Description: 
//
// Dependencies: 
//
// Revision: 
// Revision 0.01 - File Created
// Additional Comments: 
//
//////////////////////////////////////////////////////////////////////////////////
module LampCtrl(
	input wire clk,
	input wire S1,
	input wire S2,
	input wire S3,
	output wire[6 : 0] LED,
	output wire F
	);
	
	parameter C_NUM = 28;
	parameter C_MAX = 28'hFFFFFFF;
	// parameter C_NUM = 8;
	// parameter C_MAX = 8'hFF; // when simulating
	
	reg [C_NUM - 1 : 0] count;
	wire[C_NUM - 1 : 0] c_next;
	
	initial begin
		count = C_MAX;
	end
	
	assign w = S1 || S2 || S3;
	
	assign F = (count < C_MAX) ? 1'b1 : 1'b0;

	always@ (posedge clk)
	begin
		if(w == 1'b1) count = 0;
		else if(count < C_MAX) count = c_next;
	end

	assign c_next = count + 8'b1;
	
	assign LED = 7'b0000000;
	
endmodule

Lab4/src/LampCtrl_sim.v
`timescale 1ns / 1ps

////////////////////////////////////////////////////////////////////////////////
// Company: 
// Engineer:
//
// Create Date:   20:08:10 11/20/2024
// Design Name:   LampCtrl
// Module Name:   D:/LampCtrl_HDL/LampCtrl_sim.v
// Project Name:  LampCtrl_HDL
// Target Device:  
// Tool versions:  
// Description: 
//
// Verilog Test Fixture created by ISE for module: LampCtrl
//
// Dependencies:
// 
// Revision:
// Revision 0.01 - File Created
// Additional Comments:
// 
////////////////////////////////////////////////////////////////////////////////

module LampCtrl_sim;

	// Inputs
	reg clk;
	reg S1;
	reg S2;
	reg S3;

	// Outputs
	wire F;

	// Instantiate the Unit Under Test (UUT)
	LampCtrl uut (
		.clk(clk), 
		.S1(S1), 
		.S2(S2), 
		.S3(S3), 
		.F(F)
	);

	initial begin
		// Initialize Inputs
		clk = 0;
		S1 = 0;
		S2 = 0;
		S3 = 0;
		
		#600 S1 = 1;
		#20 S1 = 0;
		#6000 S2 = 1;
		#20 S2 = 0;
		#6000 S3 = 1;
		#20 S3 = 0;
	end
      
	always begin
		#10 clk = 0;
		#10 clk = 1;
	end

	initial
	begin            
		$dumpfile("./build/wave.vcd");        //生成的vcd文件名称
		$dumpvars(0, LampCtrl_sim);    //tb模块名称
		#20000 $finish;
	end
endmodule

Lab4/build/wave.vcd
$date
	Mon Apr 07 21:02:12 2025
$end
$version
	Icarus Verilog
$end
$timescale
	1ps
$end
$scope module LampCtrl_sim $end
$var wire 1 ! F $end
$var reg 1 " S1 $end
$var reg 1 # S2 $end
$var reg 1 $ S3 $end
$var reg 1 % clk $end
$scope module uut $end
$var wire 7 & LED [6:0] $end
$var wire 1 " S1 $end
$var wire 1 # S2 $end
$var wire 1 $ S3 $end
$var wire 1 % clk $end
$var wire 1 ' w $end
$var wire 8 ( c_next [7:0] $end
$var wire 1 ! F $end
$var reg 8 ) count [7:0] $end
$upscope $end
$upscope $end
$enddefinitions $end
#0
$dumpvars
b11111111 )
b0 (
0'
b0 &
0%
0$
0#
0"
0!
$end
#20000
1%
#30000
0%
#40000
1%
#50000
0%
#60000
1%
#70000
0%
#80000
1%
#90000
0%
#100000
1%
#110000
0%
#120000
1%
#130000
0%
#140000
1%
#150000
0%
#160000
1%
#170000
0%
#180000
1%
#190000
0%
#200000
1%
#210000
0%
#220000
1%
#230000
0%
#240000
1%
#250000
0%
#260000
1%
#270000
0%
#280000
1%
#290000
0%
#300000
1%
#310000
0%
#320000
1%
#330000
0%
#340000
1%
#350000
0%
#360000
1%
#370000
0%
#380000
1%
#390000
0%
#400000
1%
#410000
0%
#420000
1%
#430000
0%
#440000
1%
#450000
0%
#460000
1%
#470000
0%
#480000
1%
#490000
0%
#500000
1%
#510000
0%
#520000
1%
#530000
0%
#540000
1%
#550000
0%
#560000
1%
#570000
0%
#580000
1%
#590000
0%
#600000
1'
1%
1"
#610000
0%
#620000
1!
0'
b1 (
b0 )
1%
0"
#630000
0%
#640000
b10 (
b1 )
1%
#650000
0%
#660000
b11 (
b10 )
1%
#670000
0%
#680000
b100 (
b11 )
1%
#690000
0%
#700000
b101 (
b100 )
1%
#710000
0%
#720000
b110 (
b101 )
1%
#730000
0%
#740000
b111 (
b110 )
1%
#750000
0%
#760000
b1000 (
b111 )
1%
#770000
0%
#780000
b1001 (
b1000 )
1%
#790000
0%
#800000
b1010 (
b1001 )
1%
#810000
0%
#820000
b1011 (
b1010 )
1%
#830000
0%
#840000
b1100 (
b1011 )
1%
#850000
0%
#860000
b1101 (
b1100 )
1%
#870000
0%
#880000
b1110 (
b1101 )
1%
#890000
0%
#900000
b1111 (
b1110 )
1%
#910000
0%
#920000
b10000 (
b1111 )
1%
#930000
0%
#940000
b10001 (
b10000 )
1%
#950000
0%
#960000
b10010 (
b10001 )
1%
#970000
0%
#980000
b10011 (
b10010 )
1%
#990000
0%
#1000000
b10100 (
b10011 )
1%
#1010000
0%
#1020000
b10101 (
b10100 )
1%
#1030000
0%
#1040000
b10110 (
b10101 )
1%
#1050000
0%
#1060000
b10111 (
b10110 )
1%
#1070000
0%
#1080000
b11000 (
b10111 )
1%
#1090000
0%
#1100000
b11001 (
b11000 )
1%
#1110000
0%
#1120000
b11010 (
b11001 )
1%
#1130000
0%
#1140000
b11011 (
b11010 )
1%
#1150000
0%
#1160000
b11100 (
b11011 )
1%
#1170000
0%
#1180000
b11101 (
b11100 )
1%
#1190000
0%
#1200000
b11110 (
b11101 )
1%
#1210000
0%
#1220000
b11111 (
b11110 )
1%
#1230000
0%
#1240000
b100000 (
b11111 )
1%
#1250000
0%
#1260000
b100001 (
b100000 )
1%
#1270000
0%
#1280000
b100010 (
b100001 )
1%
#1290000
0%
#1300000
b100011 (
b100010 )
1%
#1310000
0%
#1320000
b100100 (
b100011 )
1%
#1330000
0%
#1340000
b100101 (
b100100 )
1%
#1350000
0%
#1360000
b100110 (
b100101 )
1%
#1370000
0%
#1380000
b100111 (
b100110 )
1%
#1390000
0%
#1400000
b101000 (
b100111 )
1%
#1410000
0%
#1420000
b101001 (
b101000 )
1%
#1430000
0%
#1440000
b101010 (
b101001 )
1%
#1450000
0%
#1460000
b101011 (
b101010 )
1%
#1470000
0%
#1480000
b101100 (
b101011 )
1%
#1490000
0%
#1500000
b101101 (
b101100 )
1%
#1510000
0%
#1520000
b101110 (
b101101 )
1%
#1530000
0%
#1540000
b101111 (
b101110 )
1%
#1550000
0%
#1560000
b110000 (
b101111 )
1%
#1570000
0%
#1580000
b110001 (
b110000 )
1%
#1590000
0%
#1600000
b110010 (
b110001 )
1%
#1610000
0%
#1620000
b110011 (
b110010 )
1%
#1630000
0%
#1640000
b110100 (
b110011 )
1%
#1650000
0%
#1660000
b110101 (
b110100 )
1%
#1670000
0%
#1680000
b110110 (
b110101 )
1%
#1690000
0%
#1700000
b110111 (
b110110 )
1%
#1710000
0%
#1720000
b111000 (
b110111 )
1%
#1730000
0%
#1740000
b111001 (
b111000 )
1%
#1750000
0%
#1760000
b111010 (
b111001 )
1%
#1770000
0%
#1780000
b111011 (
b111010 )
1%
#1790000
0%
#1800000
b111100 (
b111011 )
1%
#1810000
0%
#1820000
b111101 (
b111100 )
1%
#1830000
0%
#1840000
b111110 (
b111101 )
1%
#1850000
0%
#1860000
b111111 (
b111110 )
1%
#1870000
0%
#1880000
b1000000 (
b111111 )
1%
#1890000
0%
#1900000
b1000001 (
b1000000 )
1%
#1910000
0%
#1920000
b1000010 (
b1000001 )
1%
#1930000
0%
#1940000
b1000011 (
b1000010 )
1%
#1950000
0%
#1960000
b1000100 (
b1000011 )
1%
#1970000
0%
#1980000
b1000101 (
b1000100 )
1%
#1990000
0%
#2000000
b1000110 (
b1000101 )
1%
#2010000
0%
#2020000
b1000111 (
b1000110 )
1%
#2030000
0%
#2040000
b1001000 (
b1000111 )
1%
#2050000
0%
#2060000
b1001001 (
b1001000 )
1%
#2070000
0%
#2080000
b1001010 (
b1001001 )
1%
#2090000
0%
#2100000
b1001011 (
b1001010 )
1%
#2110000
0%
#2120000
b1001100 (
b1001011 )
1%
#2130000
0%
#2140000
b1001101 (
b1001100 )
1%
#2150000
0%
#2160000
b1001110 (
b1001101 )
1%
#2170000
0%
#2180000
b1001111 (
b1001110 )
1%
#2190000
0%
#2200000
b1010000 (
b1001111 )
1%
#2210000
0%
#2220000
b1010001 (
b1010000 )
1%
#2230000
0%
#2240000
b1010010 (
b1010001 )
1%
#2250000
0%
#2260000
b1010011 (
b1010010 )
1%
#2270000
0%
#2280000
b1010100 (
b1010011 )
1%
#2290000
0%
#2300000
b1010101 (
b1010100 )
1%
#2310000
0%
#2320000
b1010110 (
b1010101 )
1%
#2330000
0%
#2340000
b1010111 (
b1010110 )
1%
#2350000
0%
#2360000
b1011000 (
b1010111 )
1%
#2370000
0%
#2380000
b1011001 (
b1011000 )
1%
#2390000
0%
#2400000
b1011010 (
b1011001 )
1%
#2410000
0%
#2420000
b1011011 (
b1011010 )
1%
#2430000
0%
#2440000
b1011100 (
b1011011 )
1%
#2450000
0%
#2460000
b1011101 (
b1011100 )
1%
#2470000
0%
#2480000
b1011110 (
b1011101 )
1%
#2490000
0%
#2500000
b1011111 (
b1011110 )
1%
#2510000
0%
#2520000
b1100000 (
b1011111 )
1%
#2530000
0%
#2540000
b1100001 (
b1100000 )
1%
#2550000
0%
#2560000
b1100010 (
b1100001 )
1%
#2570000
0%
#2580000
b1100011 (
b1100010 )
1%
#2590000
0%
#2600000
b1100100 (
b1100011 )
1%
#2610000
0%
#2620000
b1100101 (
b1100100 )
1%
#2630000
0%
#2640000
b1100110 (
b1100101 )
1%
#2650000
0%
#2660000
b1100111 (
b1100110 )
1%
#2670000
0%
#2680000
b1101000 (
b1100111 )
1%
#2690000
0%
#2700000
b1101001 (
b1101000 )
1%
#2710000
0%
#2720000
b1101010 (
b1101001 )
1%
#2730000
0%
#2740000
b1101011 (
b1101010 )
1%
#2750000
0%
#2760000
b1101100 (
b1101011 )
1%
#2770000
0%
#2780000
b1101101 (
b1101100 )
1%
#2790000
0%
#2800000
b1101110 (
b1101101 )
1%
#2810000
0%
#2820000
b1101111 (
b1101110 )
1%
#2830000
0%
#2840000
b1110000 (
b1101111 )
1%
#2850000
0%
#2860000
b1110001 (
b1110000 )
1%
#2870000
0%
#2880000
b1110010 (
b1110001 )
1%
#2890000
0%
#2900000
b1110011 (
b1110010 )
1%
#2910000
0%
#2920000
b1110100 (
b1110011 )
1%
#2930000
0%
#2940000
b1110101 (
b1110100 )
1%
#2950000
0%
#2960000
b1110110 (
b1110101 )
1%
#2970000
0%
#2980000
b1110111 (
b1110110 )
1%
#2990000
0%
#3000000
b1111000 (
b1110111 )
1%
#3010000
0%
#3020000
b1111001 (
b1111000 )
1%
#3030000
0%
#3040000
b1111010 (
b1111001 )
1%
#3050000
0%
#3060000
b1111011 (
b1111010 )
1%
#3070000
0%
#3080000
b1111100 (
b1111011 )
1%
#3090000
0%
#3100000
b1111101 (
b1111100 )
1%
#3110000
0%
#3120000
b1111110 (
b1111101 )
1%
#3130000
0%
#3140000
b1111111 (
b1111110 )
1%
#3150000
0%
#3160000
b10000000 (
b1111111 )
1%
#3170000
0%
#3180000
b10000001 (
b10000000 )
1%
#3190000
0%
#3200000
b10000010 (
b10000001 )
1%
#3210000
0%
#3220000
b10000011 (
b10000010 )
1%
#3230000
0%
#3240000
b10000100 (
b10000011 )
1%
#3250000
0%
#3260000
b10000101 (
b10000100 )
1%
#3270000
0%
#3280000
b10000110 (
b10000101 )
1%
#3290000
0%
#3300000
b10000111 (
b10000110 )
1%
#3310000
0%
#3320000
b10001000 (
b10000111 )
1%
#3330000
0%
#3340000
b10001001 (
b10001000 )
1%
#3350000
0%
#3360000
b10001010 (
b10001001 )
1%
#3370000
0%
#3380000
b10001011 (
b10001010 )
1%
#3390000
0%
#3400000
b10001100 (
b10001011 )
1%
#3410000
0%
#3420000
b10001101 (
b10001100 )
1%
#3430000
0%
#3440000
b10001110 (
b10001101 )
1%
#3450000
0%
#3460000
b10001111 (
b10001110 )
1%
#3470000
0%
#3480000
b10010000 (
b10001111 )
1%
#3490000
0%
#3500000
b10010001 (
b10010000 )
1%
#3510000
0%
#3520000
b10010010 (
b10010001 )
1%
#3530000
0%
#3540000
b10010011 (
b10010010 )
1%
#3550000
0%
#3560000
b10010100 (
b10010011 )
1%
#3570000
0%
#3580000
b10010101 (
b10010100 )
1%
#3590000
0%
#3600000
b10010110 (
b10010101 )
1%
#3610000
0%
#3620000
b10010111 (
b10010110 )
1%
#3630000
0%
#3640000
b10011000 (
b10010111 )
1%
#3650000
0%
#3660000
b10011001 (
b10011000 )
1%
#3670000
0%
#3680000
b10011010 (
b10011001 )
1%
#3690000
0%
#3700000
b10011011 (
b10011010 )
1%
#3710000
0%
#3720000
b10011100 (
b10011011 )
1%
#3730000
0%
#3740000
b10011101 (
b10011100 )
1%
#3750000
0%
#3760000
b10011110 (
b10011101 )
1%
#3770000
0%
#3780000
b10011111 (
b10011110 )
1%
#3790000
0%
#3800000
b10100000 (
b10011111 )
1%
#3810000
0%
#3820000
b10100001 (
b10100000 )
1%
#3830000
0%
#3840000
b10100010 (
b10100001 )
1%
#3850000
0%
#3860000
b10100011 (
b10100010 )
1%
#3870000
0%
#3880000
b10100100 (
b10100011 )
1%
#3890000
0%
#3900000
b10100101 (
b10100100 )
1%
#3910000
0%
#3920000
b10100110 (
b10100101 )
1%
#3930000
0%
#3940000
b10100111 (
b10100110 )
1%
#3950000
0%
#3960000
b10101000 (
b10100111 )
1%
#3970000
0%
#3980000
b10101001 (
b10101000 )
1%
#3990000
0%
#4000000
b10101010 (
b10101001 )
1%
#4010000
0%
#4020000
b10101011 (
b10101010 )
1%
#4030000
0%
#4040000
b10101100 (
b10101011 )
1%
#4050000
0%
#4060000
b10101101 (
b10101100 )
1%
#4070000
0%
#4080000
b10101110 (
b10101101 )
1%
#4090000
0%
#4100000
b10101111 (
b10101110 )
1%
#4110000
0%
#4120000
b10110000 (
b10101111 )
1%
#4130000
0%
#4140000
b10110001 (
b10110000 )
1%
#4150000
0%
#4160000
b10110010 (
b10110001 )
1%
#4170000
0%
#4180000
b10110011 (
b10110010 )
1%
#4190000
0%
#4200000
b10110100 (
b10110011 )
1%
#4210000
0%
#4220000
b10110101 (
b10110100 )
1%
#4230000
0%
#4240000
b10110110 (
b10110101 )
1%
#4250000
0%
#4260000
b10110111 (
b10110110 )
1%
#4270000
0%
#4280000
b10111000 (
b10110111 )
1%
#4290000
0%
#4300000
b10111001 (
b10111000 )
1%
#4310000
0%
#4320000
b10111010 (
b10111001 )
1%
#4330000
0%
#4340000
b10111011 (
b10111010 )
1%
#4350000
0%
#4360000
b10111100 (
b10111011 )
1%
#4370000
0%
#4380000
b10111101 (
b10111100 )
1%
#4390000
0%
#4400000
b10111110 (
b10111101 )
1%
#4410000
0%
#4420000
b10111111 (
b10111110 )
1%
#4430000
0%
#4440000
b11000000 (
b10111111 )
1%
#4450000
0%
#4460000
b11000001 (
b11000000 )
1%
#4470000
0%
#4480000
b11000010 (
b11000001 )
1%
#4490000
0%
#4500000
b11000011 (
b11000010 )
1%
#4510000
0%
#4520000
b11000100 (
b11000011 )
1%
#4530000
0%
#4540000
b11000101 (
b11000100 )
1%
#4550000
0%
#4560000
b11000110 (
b11000101 )
1%
#4570000
0%
#4580000
b11000111 (
b11000110 )
1%
#4590000
0%
#4600000
b11001000 (
b11000111 )
1%
#4610000
0%
#4620000
b11001001 (
b11001000 )
1%
#4630000
0%
#4640000
b11001010 (
b11001001 )
1%
#4650000
0%
#4660000
b11001011 (
b11001010 )
1%
#4670000
0%
#4680000
b11001100 (
b11001011 )
1%
#4690000
0%
#4700000
b11001101 (
b11001100 )
1%
#4710000
0%
#4720000
b11001110 (
b11001101 )
1%
#4730000
0%
#4740000
b11001111 (
b11001110 )
1%
#4750000
0%
#4760000
b11010000 (
b11001111 )
1%
#4770000
0%
#4780000
b11010001 (
b11010000 )
1%
#4790000
0%
#4800000
b11010010 (
b11010001 )
1%
#4810000
0%
#4820000
b11010011 (
b11010010 )
1%
#4830000
0%
#4840000
b11010100 (
b11010011 )
1%
#4850000
0%
#4860000
b11010101 (
b11010100 )
1%
#4870000
0%
#4880000
b11010110 (
b11010101 )
1%
#4890000
0%
#4900000
b11010111 (
b11010110 )
1%
#4910000
0%
#4920000
b11011000 (
b11010111 )
1%
#4930000
0%
#4940000
b11011001 (
b11011000 )
1%
#4950000
0%
#4960000
b11011010 (
b11011001 )
1%
#4970000
0%
#4980000
b11011011 (
b11011010 )
1%
#4990000
0%
#5000000
b11011100 (
b11011011 )
1%
#5010000
0%
#5020000
b11011101 (
b11011100 )
1%
#5030000
0%
#5040000
b11011110 (
b11011101 )
1%
#5050000
0%
#5060000
b11011111 (
b11011110 )
1%
#5070000
0%
#5080000
b11100000 (
b11011111 )
1%
#5090000
0%
#5100000
b11100001 (
b11100000 )
1%
#5110000
0%
#5120000
b11100010 (
b11100001 )
1%
#5130000
0%
#5140000
b11100011 (
b11100010 )
1%
#5150000
0%
#5160000
b11100100 (
b11100011 )
1%
#5170000
0%
#5180000
b11100101 (
b11100100 )
1%
#5190000
0%
#5200000
b11100110 (
b11100101 )
1%
#5210000
0%
#5220000
b11100111 (
b11100110 )
1%
#5230000
0%
#5240000
b11101000 (
b11100111 )
1%
#5250000
0%
#5260000
b11101001 (
b11101000 )
1%
#5270000
0%
#5280000
b11101010 (
b11101001 )
1%
#5290000
0%
#5300000
b11101011 (
b11101010 )
1%
#5310000
0%
#5320000
b11101100 (
b11101011 )
1%
#5330000
0%
#5340000
b11101101 (
b11101100 )
1%
#5350000
0%
#5360000
b11101110 (
b11101101 )
1%
#5370000
0%
#5380000
b11101111 (
b11101110 )
1%
#5390000
0%
#5400000
b11110000 (
b11101111 )
1%
#5410000
0%
#5420000
b11110001 (
b11110000 )
1%
#5430000
0%
#5440000
b11110010 (
b11110001 )
1%
#5450000
0%
#5460000
b11110011 (
b11110010 )
1%
#5470000
0%
#5480000
b11110100 (
b11110011 )
1%
#5490000
0%
#5500000
b11110101 (
b11110100 )
1%
#5510000
0%
#5520000
b11110110 (
b11110101 )
1%
#5530000
0%
#5540000
b11110111 (
b11110110 )
1%
#5550000
0%
#5560000
b11111000 (
b11110111 )
1%
#5570000
0%
#5580000
b11111001 (
b11111000 )
1%
#5590000
0%
#5600000
b11111010 (
b11111001 )
1%
#5610000
0%
#5620000
b11111011 (
b11111010 )
1%
#5630000
0%
#5640000
b11111100 (
b11111011 )
1%
#5650000
0%
#5660000
b11111101 (
b11111100 )
1%
#5670000
0%
#5680000
b11111110 (
b11111101 )
1%
#5690000
0%
#5700000
b11111111 (
b11111110 )
1%
#5710000
0%
#5720000
0!
b0 (
b11111111 )
1%
