LabA/src/Latch.v
module SR_Latch (
    input wire S, R,
    output wire Q, Qn
);
    nand n1(Q, S, Qn);
    nand n2(Qn, R, Q);
endmodule

module CSR_Latch (
    input wire S, R, C,
    output wire Q, Qn
);
    nand n1(S1, S, C);
    nand n2(R1, R, C);
    nand n3(Q, S1, Qn);
    nand n4(Qn, R1, Q);
endmodule

module D_Latch (
    input wire D, C,
    output wire Q, Qn
);
    wire Dn;
    not n1(Dn, D);
    CSR_Latch L1(.S(D), .R(Dn), .C(C), .Q(Q), .Qn(Qn));
endmodule

LabA/src/testbench.v
`timescale 1ns/1ns
module tb_Latch;

reg clk;
reg D, S, R, C;
wire Q, Qn;

always begin
    #50 clk = ~clk;
end

always begin
    #500 C = ~C;
end

initial begin
    $dumpfile("./build/Dlatch.vcd");
    $dumpvars(0, tb_Latch);
    #90000 $finish;
end

initial begin
    clk = 0;
    D = 1;
    S = 1;
    R = 0;
    C = 0;
end

// SR_FlipFlop UUT(.S(S), .R(R), .C(C), .Q(Q), .Qn(Qn));
// T_FlipFlop UUT(.T(D), .C(C), .Q(Q), .Qn(Qn));
D_Latch UUT(.C(C), .D(D), .Q(Q), .Qn(Qn));
// This place choose which to test

always @(posedge clk) begin
    #1 D = {$random};
    #3 S = {$random};
    #3 R = {$random};
end
endmodule

LabA/build/SRlatch.vcd
$date
	Sun Apr 13 12:35:33 2025
$end
$version
	Icarus Verilog
$end
$timescale
	1ns
$end
$scope module tb_Latch $end
$var wire 1 ! Qn $end
$var wire 1 " Q $end
$var reg 1 # C $end
$var reg 1 $ D $end
$var reg 1 % R $end
$var reg 1 & S $end
$var reg 1 ' clk $end
$scope module UUT $end
$var wire 1 " Q $end
$var wire 1 ! Qn $end
$var wire 1 % R $end
$var wire 1 & S $end
$upscope $end
$upscope $end
$enddefinitions $end
#0
$dumpvars
0'
1&
0%
1$
0#
0"
1!
$end
#50
1'
#51
0$
#57
1%
#100
0'
#150
1'
#151
1$
#200
0'
#250
1'
#254
0!
1"
0&
#300
0'
#350
1'
#400
0'
#450
1'
#500
0'
1#
#550
1'
#551
0$
#554
1&
#557
0"
1!
0%
#600
0'
#650
1'
#651
1$
#700
0'
#750
1'
#754
1"
0&
#800
0'
#850
1'
#851
0$
#854
0"
1&
#900
0'
#950
1'
#951
1$
#957
1%
#1000
0'
0#
#1050
1'
#1054
0!
1"
0&
#1057
1!
0%
#1100
0'
#1150
1'
#1151
0$
#1157
0!
1%
#1200
0'
#1250
1'
#1254
1&
#1300
0'
#1350
1'
#1351
1$
#1400
0'
#1450
1'
#1451
0$
#1454
0&
#1500
0'
1#
#1550
1'
#1551
1$
#1554
1&
#1557
0"
1!
0%
#1600
0'
#1650
1'
#1651
0$
#1654
1"
0&
#1700
0'
#1750
1'
#1754
0"
1&
#1800
0'
#1850
1'
#1857
1%
#1900
0'
#1950
1'
#1954
0!
1"
0&
#1957
1!
0%
#2000
0'
0#
#2050
1'
#2057
0!
1%
#2100
0'
#2150
1'
#2151
1$
#2154
1&
#2200
0'
#2250
1'
#2254
0&
#2257
1!
0%
#2300
0'
#2350
1'
#2354
0"
1&
#2357
1%
#2400
0'
#2450
1'
#2451
0$
#2454
0!
1"
0&
#2500
0'
1#
#2550
1'
#2551
1$
#2600
0'
#2650
1'
#2700
0'
#2750
1'
#2754
1&
#2757
0"
1!
0%
#2800
0'
#2850
1'
#2900
0'
#2950
1'
#2951
0$
#2954
1"
0&
#3000
0'
0#
#3050
1'
#3051
1$
#3054
0"
1&
#3100
0'
#3150
1'
#3151
0$
#3157
1%
#3200
0'
#3250
1'
#3251
1$
#3300
0'
#3350
1'
#3351
0$
#3400
0'
#3450
1'
#3451
1$
#3454
0!
1"
0&
#3457
1!
0%
#3500
0'
1#
#3550
1'
#3551
0$
#3600
0'
#3650
1'
#3657
0!
1%
#3700
0'
#3750
1'
#3751
1$
#3754
1&
#3800
0'
#3850
1'
#3854
0&
#3900
0'
#3950
1'
#3957
1!
0%
#4000
0'
0#
#4050
1'
#4054
0"
1&
#4100
0'
#4150
1'
#4157
1%
#4200
0'
#4250
1'
#4254
0!
1"
0&
#4257
1!
0%
#4300
0'
#4350
1'
#4351
0$
#4354
0"
1&
#4400
0'
#4450
1'
#4454
1"
0&
#4457
0!
1%
#4500
0'
1#
#4550
1'
#4551
1$
#4557
1!
0%
#4600
0'
#4650
1'
#4700
0'
#4750
1'
#4751
0$
#4754
0"
1&
#4800
0'
#4850
1'
#4900
0'
#4950
1'
#4951
1$
#4957
1%
#5000
0'
0#
#5050
1'
#5057
0%
#5100
0'
#5150
1'
#5151
0$
#5154
1"
0&
#5157
0!
1%
#5200
0'
#5250
1'
#5300
0'
#5350
1'
#5351
1$
#5357
1!
0%
#5400
0'
#5450
1'
#5451
0$
#5454
0"
1&
#5457
1%
#5500
0'
1#
#5550
1'
#5554
0!
1"
0&
#5557
1!
0%
#5600
0'
#5650
1'
#5651
1$
#5654
0"
1&
#5700
0'
#5750
1'
#5751
0$
#5754
1"
0&
#5757
0!
1%
#5800
0'
#5850
1'
#5900
0'
#5950
1'
#5957
1!
0%
#6000
0'
0#
#6050
1'
#6051
1$
#6057
0!
1%
#6100
0'
#6150
1'
#6157
1!
0%
#6200
0'
#6250
1'
#6251
0$
#6257
0!
1%
#6300
0'
#6350
1'
#6357
1!
0%
#6400
0'
#6450
1'
#6454
0"
1&
#6457
1%
#6500
0'
1#
#6550
1'
#6551
1$
#6554
0!
1"
0&
#6600
0'
#6650
1'
#6654
1&
#6657
0"
1!
0%
#6700
0'
#6750
1'
#6751
0$
#6757
1%
#6800
0'
#6850
1'
#6851
1$
#6900
0'
#6950
1'
#6951
0$
#7000
0'
0#
#7050
1'
#7054
0!
1"
0&
#7057
1!
0%
#7100
0'
#7150
1'
#7154
0"
1&
#7157
1%
#7200
0'
#7250
1'
#7254
0!
1"
0&
#7300
0'
#7350
1'
#7400
0'
#7450
1'
#7500
0'
1#
#7550
1'
#7600
0'
#7650
1'
#7651
1$
#7654
1&
#7657
0"
1!
0%
#7700
0'
#7750
1'
#7751
0$
#7754
1"
0&
#7757
0!
1%
#7800
0'
#7850
1'
#7900
0'
#7950
1'
#7957
1!
0%
#8000
0'
0#
#8050
1'
#8054
0"
1&
#8100
0'
#8150
1'
#8154
1"
0&
#8157
0!
1%
#8200
0'
#8250
1'
#8251
1$
#8300
0'
#8350
1'
#8354
1&
#8400
0'
#8450
1'
#8451
0$
#8500
0'
1#
#8550
1'
#8551
1$
#8554
0&
#8557
1!
0%
#8600
0'
#8650
1'
#8700
0'
#8750
1'
#8754
0"
1&
#8800
0'
#8850
1'
#8851
0$
#8900
0'
#8950
1'
#9000
0'
0#
#9050
1'
#9051
1$
#9100
0'
#9150
1'
#9154
1"
0&
#9157
0!
1%
#9200
0'
#9250
1'
#9251
0$
#9300
0'
#9350
1'
#9357
1!
0%
#9400
0'
#9450
1'
#9451
1$
#9454
0"
1&
#9457
1%
#9500
0'
1#
#9550
1'
#9557
0%
#9600
0'
#9650
1'
#9657
1%
#9700
0'
#9750
1'
#9751
0$
#9754
0!
1"
0&
#9757
1!
0%
#9800
0'
#9850
1'
#9900
0'
#9950
1'
#9951
1$
#9954
0"
1&
#9957
1%
#10000
0'
0#
#10050
1'
#10100
0'
#10150
1'
#10154
0!
1"
0&
#10200
0'
#10250
1'
#10254
1&
#10300
0'
#10350
1'
#10400
0'
#10450
1'
#10454
0&
#10457
1!
0%
#10500
0'
1#
#10550
1'
#10554
0"
1&
#10600
0'
#10650
1'
#10651
0$
#10654
1"
0&
#10700
0'
#10750
1'
#10751
1$
#10800
0'
#10850
1'
#10851
0$
#10900
0'
#10950
1'
#10954
0"
1&
#11000
0'
0#
#11050
1'
#11100
0'
#11150
1'
#11154
1"
0&
#11200
0'
#11250
1'
#11251
1$
#11254
0"
1&
#11257
1%
#11300
0'
#11350
1'
#11357
0%
#11400
0'
#11450
1'
#11457
1%
#11500
0'
1#
#11550
1'
#11551
0$
#11557
0%
#11600
0'
#11650
1'
#11657
1%
#11700
0'
#11750
1'
#11757
0%
#11800
0'
#11850
1'
#11900
0'
#11950
1'
#11954
1"
0&
#12000
0'
0#
#12050
1'
#12051
1$
#12054
0"
1&
#12057
1%
#12100
0'
#12150
1'
#12154
0!
1"
0&
#12200
0'
#12250
1'
#12254
1&
#12300
0'
#12350
1'
#12400
0'
#12450
1'
#12451
0$
#12457
0"
1!
0%
#12500
0'
1#
#12550
1'
#12551
1$
#12554
1"
0&
#12600
0'
#12650
1'
#12700
0'
#12750
1'
#12751
0$
#12800
0'
#12850
1'
#12851
1$
#12900
0'
#12950
1'
#12951
0$
#13000
0'
0#
#13050
1'
#13054
0"
1&
#13100
0'
#13150
1'
#13151
1$
#13154
1"
0&
#13200
0'
#13250
1'
#13257
0!
1%
#13300
0'
#13350
1'
#13400
0'
#13450
1'
#13451
0$
#13454
1&
#13457
0"
1!
0%
#13500
0'
1#
#13550
1'
#13554
1"
0&
#13600
0'
#13650
1'
#13651
1$
#13657
0!
1%
#13700
0'
#13750
1'
#13751
0$
#13754
1&
#13800
0'
#13850
1'
#13857
0"
1!
0%
#13900
0'
#13950
1'
#13951
1$
#13957
1%
#14000
0'
0#
#14050
1'
#14051
0$
#14100
0'
#14150
1'
#14154
0!
1"
0&
#14200
0'
#14250
1'
#14251
1$
#14257
1!
0%
#14300
0'
#14350
1'
#14354
0"
1&
#14400
0'
#14450
1'
#14451
0$
#14500
0'
1#
#14550
1'
#14557
1%
#14600
0'
#14650
1'
#14654
0!
1"
0&
#14700
0'
#14750
1'
#14800
0'
#14850
1'
#14851
1$
#14900
0'
#14950
1'
#14951
0$
#14954
1&
#15000
0'
0#
#15050
1'
#15100
0'
#15150
1'
#15151
1$
#15154
0&
#15200
0'
#15250
1'
#15254
1&
#15257
0"
1!
0%
#15300
0'
#15350
1'
#15351
0$
#15400
0'
#15450
1'
#15500
0'
1#
#15550
1'
#15557
1%
#15600
0'
#15650
1'
#15657
0%
#15700
0'
#15750
1'
#15751
1$
#15757
1%
#15800
0'
#15850
1'
#15854
0!
1"
0&
#15857
1!
0%
#15900
0'
#15950
1'
#15957
0!
1%
#16000
0'
0#
#16050
1'
#16051
0$
#16054
1&
#16100
0'
#16150
1'
#16154
0&
#16200
0'
#16250
1'
#16251
1$
#16254
1&
#16257
0"
1!
0%
#16300
0'
#16350
1'
#16351
0$
#16400
0'
#16450
1'
#16457
1%
#16500
0'
1#
#16550
1'
#16551
1$
#16554
0!
1"
0&
#16600
0'
#16650
1'
#16657
1!
0%
#16700
0'
#16750
1'
#16751
0$
#16754
0"
1&
#16757
1%
#16800
0'
#16850
1'
#16851
1$
#16854
0!
1"
0&
#16857
1!
0%
#16900
0'
#16950
1'
#16951
0$
#16954
0"
1&
#16957
1%
#17000
0'
0#
#17050
1'
#17051
1$
#17057
0%
#17100
0'
#17150
1'
#17157
1%
#17200
0'
#17250
1'
#17300
0'
#17350
1'
#17354
0!
1"
0&
#17400
0'
#17450
1'
#17451
0$
#17457
1!
0%
#17500
0'
1#
#17550
1'
#17551
1$
#17554
0"
1&
#17557
1%
#17600
0'
#17650
1'
#17700
0'
#17750
1'
#17800
0'
#17850
1'
#17851
0$
#17854
0!
1"
0&
#17857
1!
0%
#17900
0'
#17950
1'
#17951
1$
#18000
0'
0#
#18050
1'
#18051
0$
#18054
0"
1&
#18057
1%
#18100
0'
#18150
1'
#18154
0!
1"
0&
#18157
1!
0%
#18200
0'
#18250
1'
#18251
1$
#18254
0"
1&
#18300
0'
#18350
1'
#18354
1"
0&
#18357
0!
1%
#18400
0'
#18450
1'
#18451
0$
#18457
1!
0%
#18500
0'
1#
#18550
1'
#18551
1$
#18554
0"
1&
#18557
1%
#18600
0'
#18650
1'
#18651
0$
#18657
0%
#18700
0'
#18750
1'
#18751
1$
#18754
1"
0&
#18757
0!
1%
#18800
0'
#18850
1'
#18857
1!
0%
#18900
0'
#18950
1'
#18951
0$
#18957
0!
1%
#19000
0'
0#
#19050
1'
#19051
1$
#19057
1!
0%
#19100
0'
#19150
1'
#19157
0!
1%
#19200
0'
#19250
1'
#19251
0$
#19254
1&
#19300
0'
#19350
1'
#19400
0'
#19450
1'
#19454
0&
#19457
1!
0%
#19500
0'
1#
#19550
1'
#19554
0"
1&
#19557
1%
#19600
0'
#19650
1'
#19651
1$
#19700
0'
#19750
1'
#19751
0$
#19754
0!
1"
0&
#19757
1!
0%
#19800
0'
#19850
1'
#19900
0'
#19950
1'
#19954
0"
1&
#19957
1%
#20000
0'
0#
#20050
1'
#20051
1$
#20100
0'
#20150
1'
#20157
0%
#20200
0'
#20250
1'
#20251
0$
#20254
1"
0&
#20300
0'
#20350
1'
#20357
0!
1%
#20400
0'
#20450
1'
#20451
1$
#20500
0'
1#
#20550
1'
#20551
0$
#20554
1&
#20600
0'
#20650
1'
#20651
1$
#20654
0&
#20657
1!
0%
#20700
0'
#20750
1'
#20751
0$
#20754
0"
1&
#20757
1%
#20800
0'
#20850
1'
#20857
0%
#20900
0'
#20950
1'
#20954
1"
0&
#21000
0'
0#
#21050
1'
#21057
0!
1%
#21100
0'
#21150
1'
#21200
0'
#21250
1'
#21300
0'
#21350
1'
#21351
1$
#21354
1&
#21357
0"
1!
0%
#21400
0'
#21450
1'
#21451
0$
#21457
1%
#21500
0'
1#
#21550
1'
#21551
1$
#21557
0%
#21600
0'
#21650
1'
#21657
1%
#21700
0'
#21750
1'
#21754
0!
1"
0&
#21800
0'
#21850
1'
#21851
0$
#21900
0'
#21950
1'
#22000
0'
0#
#22050
1'
#22057
1!
0%
#22100
0'
#22150
1'
#22200
0'
#22250
1'
#22251
1$
#22254
0"
1&
#22300
0'
#22350
1'
#22351
0$
#22357
1%
#22400
0'
#22450
1'
#22451
1$
#22500
0'
1#
#22550
1'
#22557
0%
#22600
0'
#22650
1'
#22654
1"
0&
#22700
0'
#22750
1'
#22751
0$
#22754
0"
1&
#22757
1%
#22800
0'
#22850
1'
#22900
0'
#22950
1'
#22951
1$
#22954
0!
1"
0&
#22957
1!
0%
#23000
0'
0#
#23050
1'
#23051
0$
#23057
0!
1%
#23100
0'
#23150
1'
#23151
1$
#23154
1&
#23157
0"
1!
0%
#23200
0'
#23250
1'
#23254
1"
0&
#23300
0'
#23350
1'
#23351
0$
#23400
0'
#23450
1'
#23457
0!
1%
#23500
0'
1#
#23550
1'
#23600
0'
#23650
1'
#23651
1$
#23654
1&
#23700
0'
#23750
1'
#23754
0&
#23757
1!
0%
#23800
0'
#23850
1'
#23851
0$
#23857
0!
1%
#23900
0'
#23950
1'
#23951
1$
#23957
1!
0%
#24000
0'
0#
#24050
1'
#24054
0"
1&
#24057
1%
#24100
0'
#24150
1'
#24157
0%
#24200
0'
#24250
1'
#24251
0$
#24254
1"
0&
#24257
0!
1%
#24300
0'
#24350
1'
#24354
1&
#24357
0"
1!
0%
#24400
0'
#24450
1'
#24454
1"
0&
#24500
0'
1#
#24550
1'
#24554
0"
1&
#24600
0'
#24650
1'
#24651
1$
#24700
0'
#24750
1'
#24800
0'
#24850
1'
#24854
1"
0&
#24857
0!
1%
#24900
0'
#24950
1'
#24957
1!
0%
#25000
0'
0#
#25050
1'
#25054
0"
1&
#25100
0'
#25150
1'
#25151
0$
#25154
1"
0&
#25200
0'
#25250
1'
#25251
1$
#25254
0"
1&
#25257
1%
#25300
0'
#25350
1'
#25351
0$
#25354
0!
1"
0&
#25400
0'
#25450
1'
#25451
1$
#25454
1&
#25500
0'
1#
#25550
1'
#25551
0$
#25554
0&
#25600
0'
#25650
1'
#25651
1$
#25657
1!
0%
#25700
0'
#25750
1'
#25757
0!
1%
#25800
0'
#25850
1'
#25851
0$
#25854
1&
#25900
0'
#25950
1'
#25954
0&
#25957
1!
0%
#26000
0'
0#
#26050
1'
#26057
0!
1%
#26100
0'
#26150
1'
#26154
1&
#26157
0"
1!
0%
#26200
0'
#26250
1'
#26254
1"
0&
#26257
0!
1%
#26300
0'
#26350
1'
#26400
0'
#26450
1'
#26454
1&
#26500
0'
1#
#26550
1'
#26551
1$
#26600
0'
#26650
1'
#26651
0$
#26700
0'
#26750
1'
#26754
0&
#26800
0'
#26850
1'
#26854
1&
#26900
0'
#26950
1'
#26951
1$
#27000
0'
0#
#27050
1'
#27051
0$
#27057
0"
1!
0%
#27100
0'
#27150
1'
#27151
1$
#27154
1"
0&
#27157
0!
1%
#27200
0'
#27250
1'
#27257
1!
0%
#27300
0'
#27350
1'
#27351
0$
#27357
0!
1%
#27400
0'
#27450
1'
#27451
1$
#27457
1!
0%
#27500
0'
1#
#27550
1'
#27554
0"
1&
#27557
1%
#27600
0'
#27650
1'
#27657
0%
#27700
0'
#27750
1'
#27751
0$
#27754
1"
0&
#27800
0'
#27850
1'
#27851
1$
#27900
0'
#27950
1'
#27957
0!
1%
#28000
0'
0#
#28050
1'
#28051
0$
#28100
0'
#28150
1'
#28157
1!
0%
#28200
0'
#28250
1'
#28254
0"
1&
#28300
0'
#28350
1'
#28351
1$
#28400
0'
#28450
1'
#28451
0$
#28500
0'
1#
#28550
1'
#28551
1$
#28557
1%
#28600
0'
#28650
1'
#28654
0!
1"
0&
#28700
0'
#28750
1'
#28751
0$
#28800
0'
#28850
1'
#28851
1$
#28854
1&
#28857
0"
1!
0%
#28900
0'
#28950
1'
#28957
1%
#29000
0'
0#
#29050
1'
#29100
0'
#29150
1'
#29151
0$
#29157
0%
#29200
0'
#29250
1'
#29254
1"
0&
#29257
0!
1%
#29300
0'
#29350
1'
#29354
1&
#29357
0"
1!
0%
#29400
0'
#29450
1'
#29451
1$
#29454
1"
0&
#29500
0'
1#
#29550
1'
#29551
0$
#29557
0!
1%
#29600
0'
#29650
1'
#29700
0'
#29750
1'
#29754
1&
#29757
0"
1!
0%
#29800
0'
#29850
1'
#29857
1%
#29900
0'
#29950
1'
#29954
0!
1"
0&
#30000
0'
0#
#30050
1'
#30051
1$
#30100
0'
#30150
1'
#30154
1&
#30200
0'
#30250
1'
#30251
0$
#30257
0"
1!
0%
#30300
0'
#30350
1'
#30357
1%
#30400
0'
#30450
1'
#30500
0'
1#
#30550
1'
#30600
0'
#30650
1'
#30651
1$
#30654
0!
1"
0&
#30700
0'
#30750
1'
#30751
0$
#30754
1&
#30757
0"
1!
0%
#30800
0'
#30850
1'
#30854
1"
0&
#30900
0'
#30950
1'
#31000
0'
0#
#31050
1'
#31057
0!
1%
#31100
0'
#31150
1'
#31151
1$
#31154
1&
#31157
0"
1!
0%
#31200
0'
#31250
1'
#31251
0$
#31254
1"
0&
#31257
0!
1%
#31300
0'
#31350
1'
#31351
1$
#31400
0'
#31450
1'
#31454
1&
#31457
0"
1!
0%
#31500
0'
1#
#31550
1'
#31551
0$
#31557
1%
#31600
0'
#31650
1'
#31654
0!
1"
0&
#31657
1!
0%
#31700
0'
#31750
1'
#31754
0"
1&
#31800
0'
#31850
1'
#31851
1$
#31900
0'
#31950
1'
#31954
1"
0&
#31957
0!
1%
#32000
0'
0#
#32050
1'
#32100
0'
#32150
1'
#32154
1&
#32200
0'
#32250
1'
#32251
0$
#32257
0"
1!
0%
#32300
0'
#32350
1'
#32351
1$
#32354
1"
0&
#32400
0'
#32450
1'
#32451
0$
#32457
0!
1%
#32500
0'
1#
#32550
1'
#32554
1&
#32557
0"
1!
0%
#32600
0'
#32650
1'
#32657
1%
#32700
0'
#32750
1'
#32751
1$
#32757
0%
#32800
0'
#32850
1'
#32857
1%
#32900
0'
#32950
1'
#32951
0$
#32954
0!
1"
0&
#33000
0'
0#
#33050
1'
#33051
1$
#33054
1&
#33057
0"
1!
0%
#33100
0'
#33150
1'
#33200
0'
#33250
1'
#33251
0$
#33300
0'
#33350
1'
#33357
1%
#33400
0'
#33450
1'
#33454
0!
1"
0&
#33500
0'
1#
#33550
1'
#33557
1!
0%
#33600
0'
#33650
1'
#33651
1$
#33654
0"
1&
#33657
1%
#33700
0'
#33750
1'
#33800
0'
#33850
1'
#33851
0$
#33857
0%
#33900
0'
#33950
1'
#33951
1$
#33954
1"
0&
#33957
0!
1%
#34000
0'
0#
#34050
1'
#34051
0$
#34054
1&
#34057
0"
1!
0%
#34100
0'
#34150
1'
#34151
1$
#34154
1"
0&
#34157
0!
1%
#34200
0'
#34250
1'
#34251
0$
#34254
1&
#34257
0"
1!
0%
#34300
0'
#34350
1'
#34354
1"
0&
#34357
0!
1%
#34400
0'
#34450
1'
#34500
0'
1#
#34550
1'
#34551
1$
#34554
1&
#34600
0'
#34650
1'
#34654
0&
#34700
0'
#34750
1'
#34800
0'
#34850
1'
#34851
0$
#34854
1&
#34900
0'
#34950
1'
#34951
1$
#35000
0'
0#
#35050
1'
#35051
0$
#35057
0"
1!
0%
#35100
0'
#35150
1'
#35151
1$
#35157
1%
#35200
0'
#35250
1'
#35254
0!
1"
0&
#35300
0'
#35350
1'
#35354
1&
#35400
0'
#35450
1'
#35451
0$
#35454
0&
#35457
1!
0%
#35500
0'
1#
#35550
1'
#35551
1$
#35554
0"
1&
#35600
0'
#35650
1'
#35651
0$
#35654
1"
0&
#35657
0!
1%
#35700
0'
#35750
1'
#35751
1$
#35754
1&
#35757
0"
1!
0%
#35800
0'
#35850
1'
#35851
0$
#35900
0'
#35950
1'
#35954
1"
0&
#36000
0'
0#
#36050
1'
#36057
0!
1%
#36100
0'
#36150
1'
#36151
1$
#36157
1!
0%
#36200
0'
#36250
1'
#36251
0$
#36300
0'
#36350
1'
#36351
1$
#36354
0"
1&
#36357
1%
#36400
0'
#36450
1'
#36457
0%
#36500
0'
1#
#36550
1'
#36551
0$
#36554
1"
0&
#36600
0'
#36650
1'
#36651
1$
#36654
0"
1&
#36657
1%
#36700
0'
#36750
1'
#36757
0%
#36800
0'
#36850
1'
#36851
0$
#36854
1"
0&
#36857
0!
1%
#36900
0'
#36950
1'
#36957
1!
0%
#37000
0'
0#
#37050
1'
#37051
1$
#37057
0!
1%
#37100
0'
#37150
1'
#37154
1&
#37200
0'
#37250
1'
#37251
0$
#37254
0&
#37257
1!
0%
#37300
0'
#37350
1'
#37351
1$
#37354
0"
1&
#37357
1%
#37400
0'
#37450
1'
#37451
0$
#37454
0!
1"
0&
#37457
1!
0%
#37500
0'
1#
#37550
1'
#37557
0!
1%
#37600
0'
#37650
1'
#37651
1$
#37654
1&
#37657
0"
1!
0%
#37700
0'
#37750
1'
#37751
0$
#37754
1"
0&
#37757
0!
1%
#37800
0'
#37850
1'
#37854
1&
#37857
0"
1!
0%
#37900
0'
#37950
1'
#37951
1$
#37957
1%
#38000
0'
0#
#38050
1'
#38054
0!
1"
0&
#38100
0'
#38150
1'
#38157
1!
0%
#38200
0'
#38250
1'
#38300
0'
#38350
1'
#38351
0$
#38354
0"
1&
#38400
0'
#38450
1'
#38500
0'
1#
#38550
1'
#38551
1$
#38557
1%
#38600
0'
#38650
1'
#38651
0$
#38657
0%
#38700
0'
#38750
1'
#38751
1$
#38757
1%
#38800
0'
#38850
1'
#38851
0$
#38854
0!
1"
0&
#38857
1!
0%
#38900
0'
#38950
1'
#39000
0'
0#
#39050
1'
#39054
0"
1&
#39057
1%
#39100
0'
#39150
1'
#39151
1$
#39200
0'
#39250
1'
#39257
0%
#39300
0'
#39350
1'
#39351
0$
#39357
1%
#39400
0'
#39450
1'
#39451
1$
#39454
0!
1"
0&
#39500
0'
1#
#39550
1'
#39600
0'
#39650
1'
#39651
0$
#39654
1&
#39700
0'
#39750
1'
#39751
1$
#39754
0&
#39800
0'
#39850
1'
#39851
0$
#39854
1&
#39900
0'
#39950
1'
#39954
0&
#39957
1!
0%
#40000
0'
0#
#40050
1'
#40051
1$
#40100
0'
#40150
1'
#40151
0$
#40200
0'
#40250
1'
#40251
1$
#40300
0'
#40350
1'
#40351
0$
#40354
0"
1&
#40400
0'
#40450
1'
#40451
1$
#40500
0'
1#
#40550
1'
#40554
1"
0&
#40600
0'
#40650
1'
#40651
0$
#40657
0!
1%
#40700
0'
#40750
1'
#40751
1$
#40754
1&
#40800
0'
#40850
1'
#40851
0$
#40854
0&
#40900
0'
#40950
1'
#40954
1&
#41000
0'
0#
#41050
1'
#41051
1$
#41054
0&
#41100
0'
#41150
1'
#41200
0'
#41250
1'
#41254
1&
#41300
0'
#41350
1'
#41351
0$
#41354
0&
#41357
1!
0%
#41400
0'
#41450
1'
#41451
1$
#41454
0"
1&
#41457
1%
#41500
0'
1#
#41550
1'
#41551
0$
#41557
0%
#41600
0'
#41650
1'
#41657
1%
#41700
0'
#41750
1'
#41754
0!
1"
0&
#41800
0'
#41850
1'
#41854
1&
#41857
0"
1!
0%
#41900
0'
#41950
1'
#41951
1$
#42000
0'
0#
#42050
1'
#42057
1%
#42100
0'
#42150
1'
#42151
0$
#42154
0!
1"
0&
#42157
1!
0%
#42200
0'
#42250
1'
#42251
1$
#42300
0'
#42350
1'
#42400
0'
#42450
1'
#42500
0'
1#
#42550
1'
#42554
0"
1&
#42600
0'
#42650
1'
#42651
0$
#42654
1"
0&
#42657
0!
1%
#42700
0'
#42750
1'
#42751
1$
#42800
0'
#42850
1'
#42900
0'
#42950
1'
#42951
0$
#42954
1&
#43000
0'
0#
#43050
1'
#43051
1$
#43054
0&
#43100
0'
#43150
1'
#43200
0'
#43250
1'
#43251
0$
#43254
1&
#43257
0"
1!
0%
#43300
0'
#43350
1'
#43357
1%
#43400
0'
#43450
1'
#43451
1$
#43457
0%
#43500
0'
1#
#43550
1'
#43551
0$
#43557
1%
#43600
0'
#43650
1'
#43651
1$
#43654
0!
1"
0&
#43657
1!
0%
#43700
0'
#43750
1'
#43754
0"
1&
#43800
0'
#43850
1'
#43857
1%
#43900
0'
#43950
1'
#43954
0!
1"
0&
#44000
0'
0#
#44050
1'
#44051
0$
#44057
1!
0%
#44100
0'
#44150
1'
#44151
1$
#44200
0'
#44250
1'
#44257
0!
1%
#44300
0'
#44350
1'
#44351
0$
#44357
1!
0%
#44400
0'
#44450
1'
#44451
1$
#44500
0'
1#
#44550
1'
#44551
0$
#44554
0"
1&
#44557
1%
#44600
0'
#44650
1'
#44700
0'
#44750
1'
#44754
0!
1"
0&
#44757
1!
0%
#44800
0'
#44850
1'
#44851
1$
#44857
0!
1%
#44900
0'
#44950
1'
#45000
0'
0#
#45050
1'
#45051
0$
#45054
1&
#45057
0"
1!
0%
#45100
0'
#45150
1'
#45151
1$
#45154
1"
0&
#45157
0!
1%
#45200
0'
#45250
1'
#45300
0'
#45350
1'
#45400
0'
#45450
1'
#45451
0$
#45454
1&
#45457
0"
1!
0%
#45500
0'
1#
#45550
1'
#45600
0'
#45650
1'
#45654
1"
0&
#45657
0!
1%
#45700
0'
#45750
1'
#45757
1!
0%
#45800
0'
#45850
1'
#45900
0'
#45950
1'
#45954
0"
1&
#45957
1%
#46000
0'
0#
#46050
1'
#46051
1$
#46054
0!
1"
0&
#46057
1!
0%
#46100
0'
#46150
1'
#46157
0!
1%
#46200
0'
#46250
1'
#46254
1&
#46300
0'
#46350
1'
#46354
0&
#46357
1!
0%
#46400
0'
#46450
1'
#46451
0$
#46500
0'
1#
#46550
1'
#46551
1$
#46554
0"
1&
#46557
1%
#46600
0'
#46650
1'
#46654
0!
1"
0&
#46657
1!
0%
#46700
0'
#46750
1'
#46751
0$
#46754
0"
1&
#46757
1%
#46800
0'
#46850
1'
#46851
1$
#46854
0!
1"
0&
#46900
0'
#46950
1'
#46951
0$
#46954
1&
#46957
0"
1!
0%
#47000
0'
0#
#47050
1'
#47054
1"
0&
#47100
0'
#47150
1'
#47200
0'
#47250
1'
#47300
0'
#47350
1'
#47351
1$
#47354
0"
1&
#47357
1%
#47400
0'
#47450
1'
#47457
0%
#47500
0'
1#
#47550
1'
#47551
0$
#47557
1%
#47600
0'
#47650
1'
#47657
0%
#47700
0'
#47750
1'
#47751
1$
#47754
1"
0&
#47800
0'
#47850
1'
#47851
0$
#47857
0!
1%
#47900
0'
#47950
1'
#47951
1$
#47954
1&
#47957
0"
1!
0%
#48000
0'
0#
#48050
1'
#48100
0'
#48150
1'
#48154
1"
0&
#48200
0'
#48250
1'
#48251
0$
#48254
0"
1&
#48257
1%
#48300
0'
#48350
1'
#48354
0!
1"
0&
#48400
0'
#48450
1'
#48451
1$
#48454
1&
#48500
0'
1#
#48550
1'
#48554
0&
#48557
1!
0%
#48600
0'
#48650
1'
#48651
0$
#48654
0"
1&
#48657
1%
#48700
0'
#48750
1'
#48757
0%
#48800
0'
#48850
1'
#48851
1$
#48857
1%
#48900
0'
#48950
1'
#48951
0$
#48957
0%
#49000
0'
0#
#49050
1'
#49054
1"
0&
#49100
0'
#49150
1'
#49151
1$
#49157
0!
1%
#49200
0'
#49250
1'
#49257
1!
0%
#49300
0'
#49350
1'
#49351
0$
#49354
0"
1&
#49357
1%
#49400
0'
#49450
1'
#49457
0%
#49500
0'
1#
#49550
1'
#49551
1$
#49600
0'
#49650
1'
#49657
1%
#49700
0'
#49750
1'
#49751
0$
#49800
0'
#49850
1'
#49851
1$
#49857
0%
#49900
0'
#49950
1'
#49957
1%
#50000
0'
0#
#50050
1'
#50057
0%
#50100
0'
#50150
1'
#50157
1%
#50200
0'
#50250
1'
#50251
0$
#50257
0%
#50300
0'
#50350
1'
#50351
1$
#50400
0'
#50450
1'
#50454
1"
0&
#50500
0'
1#
#50550
1'
#50551
0$
#50557
0!
1%
#50600
0'
#50650
1'
#50654
1&
#50657
0"
1!
0%
#50700
0'
#50750
1'
#50751
1$
#50800
0'
#50850
1'
#50851
0$
#50900
0'
#50950
1'
#50951
1$
#50957
1%
#51000
0'
0#
#51050
1'
#51054
0!
1"
0&
#51100
0'
#51150
1'
#51200
0'
#51250
1'
#51251
0$
#51254
1&
#51300
0'
#51350
1'
#51400
0'
#51450
1'
#51454
0&
#51500
0'
1#
